dospaces/__init__.py
dospaces/callbacks.py
dospaces/spaces.py
dospaces-0.1.dist-info/LICENSE
dospaces-0.1.dist-info/WHEEL
dospaces-0.1.dist-info/METADATA
dospaces-0.1.dist-info/RECORD
