Metadata-Version: 2.1
Name: dospaces
Version: 0.1
Summary: Limited python wrapper for DigitalOcean Spaces
Author-email: Alyetama <56323389+Alyetama@users.noreply.github.com>
Classifier: License :: OSI Approved :: MIT License
Requires-Dist: boto3 >=1.16.63
Requires-Dist: python-dotenv >=0.19.2
Requires-Dist: loguru >=0.5.3
Requires-Dist: tqdm >=4.62.3
Project-URL: Home, https://github.com/Alyetama/Python-DigitalOceanSpaces
